{"paging":{"pageIndex":1,"pageSize":500,"total":23},"baseComponent":{"id":"AYk7c1-pzYM99Xq-1JyY","key":"fga-eps-mds-1_2023-1-capju-services-unit","name":"2023-1-CAPJu-Services-Unit","qualifier":"TRK","measures":[{"metric":"duplicated_lines_density","value":"0.0","bestValue":true},{"metric":"functions","value":"18"},{"metric":"security_rating","value":"1.0","bestValue":true},{"metric":"files","value":"13"},{"metric":"complexity","value":"27"},{"metric":"ncloc","value":"285"},{"metric":"coverage","value":"0.0","bestValue":false},{"metric":"comment_lines_density","value":"0.7","bestValue":false}]},"components":[{"id":"AYk7nSYRbtttg9wbGYMj","key":"fga-eps-mds-1_2023-1-capju-services-unit:src/migrations/001-CreateUnit.cjs","name":"001-CreateUnit.cjs","qualifier":"FIL","path":"src/migrations/001-CreateUnit.cjs","language":"js","measures":[{"metric":"complexity","value":"2"},{"metric":"functions","value":"2"},{"metric":"ncloc","value":"28"},{"metric":"coverage","value":"0.0","bestValue":false},{"metric":"security_rating","value":"1.0","bestValue":true},{"metric":"comment_lines_density","value":"3.4","bestValue":false},{"metric":"files","value":"1"},{"metric":"duplicated_lines_density","value":"0.0","bestValue":true},{"metric":"test_errors","value":"0","bestValue":true},{"metric":"test_failures","value":"0","bestValue":true}]},{"id":"AYk7nSYRbtttg9wbGYMa","key":"fga-eps-mds-1_2023-1-capju-services-unit:src/models/_index.js","name":"_index.js","qualifier":"FIL","path":"src/models/_index.js","language":"js","measures":[{"metric":"complexity","value":"0"},{"metric":"functions","value":"0"},{"metric":"ncloc","value":"6"},{"metric":"coverage","value":"0.0","bestValue":false},{"metric":"security_rating","value":"1.0","bestValue":true},{"metric":"comment_lines_density","value":"0.0","bestValue":false},{"metric":"files","value":"1"},{"metric":"duplicated_lines_density","value":"0.0","bestValue":true},{"metric":"test_errors","value":"0","bestValue":true},{"metric":"test_failures","value":"0","bestValue":true}]},{"id":"AYk7nSYRbtttg9wbGYMg","key":"fga-eps-mds-1_2023-1-capju-services-unit:src/controllers/_index.js","name":"_index.js","qualifier":"FIL","path":"src/controllers/_index.js","language":"js","measures":[{"metric":"complexity","value":"0"},{"metric":"functions","value":"0"},{"metric":"ncloc","value":"6"},{"metric":"coverage","value":"0.0","bestValue":false},{"metric":"security_rating","value":"1.0","bestValue":true},{"metric":"comment_lines_density","value":"0.0","bestValue":false},{"metric":"files","value":"1"},{"metric":"duplicated_lines_density","value":"0.0","bestValue":true},{"metric":"test_errors","value":"0","bestValue":true},{"metric":"test_failures","value":"0","bestValue":true}]},{"id":"AYk7nSYRbtttg9wbGYMb","key":"fga-eps-mds-1_2023-1-capju-services-unit:src/routes/_index.js","name":"_index.js","qualifier":"FIL","path":"src/routes/_index.js","language":"js","measures":[{"metric":"complexity","value":"0"},{"metric":"functions","value":"0"},{"metric":"ncloc","value":"5"},{"metric":"coverage","value":"0.0","bestValue":false},{"metric":"security_rating","value":"1.0","bestValue":true},{"metric":"comment_lines_density","value":"0.0","bestValue":false},{"metric":"files","value":"1"},{"metric":"duplicated_lines_density","value":"0.0","bestValue":true},{"metric":"test_errors","value":"0","bestValue":true},{"metric":"test_failures","value":"0","bestValue":true}]},{"id":"AYk7nSYRbtttg9wbGYMd","key":"fga-eps-mds-1_2023-1-capju-services-unit:src/services/_index.js","name":"_index.js","qualifier":"FIL","path":"src/services/_index.js","language":"js","measures":[{"metric":"complexity","value":"0"},{"metric":"functions","value":"0"},{"metric":"ncloc","value":"7"},{"metric":"coverage","value":"0.0","bestValue":false},{"metric":"security_rating","value":"1.0","bestValue":true},{"metric":"comment_lines_density","value":"0.0","bestValue":false},{"metric":"files","value":"1"},{"metric":"duplicated_lines_density","value":"0.0","bestValue":true},{"metric":"test_errors","value":"0","bestValue":true},{"metric":"test_failures","value":"0","bestValue":true}]},{"id":"AYk7h8KaMxBJGWHr585J","key":"fga-eps-mds-1_2023-1-capju-services-unit:src/config","name":"config","qualifier":"DIR","path":"src/config","measures":[{"metric":"duplicated_lines_density","value":"0.0","bestValue":true},{"metric":"functions","value":"0"},{"metric":"security_rating","value":"1.0","bestValue":true},{"metric":"files","value":"2"},{"metric":"complexity","value":"0"},{"metric":"ncloc","value":"14"},{"metric":"coverage","value":"0.0","bestValue":false},{"metric":"comment_lines_density","value":"0.0","bestValue":false}]},{"id":"AYk7h8KaMxBJGWHr585F","key":"fga-eps-mds-1_2023-1-capju-services-unit:src/controllers","name":"controllers","qualifier":"DIR","path":"src/controllers","measures":[{"metric":"duplicated_lines_density","value":"0.0","bestValue":true},{"metric":"functions","value":"7"},{"metric":"security_rating","value":"1.0","bestValue":true},{"metric":"files","value":"2"},{"metric":"complexity","value":"12"},{"metric":"ncloc","value":"126"},{"metric":"coverage","value":"0.0","bestValue":false},{"metric":"comment_lines_density","value":"0.8","bestValue":false}]},{"id":"AYk7h8KaMxBJGWHr585I","key":"fga-eps-mds-1_2023-1-capju-services-unit:src/config/database.js","name":"database.js","qualifier":"FIL","path":"src/config/database.js","language":"js","measures":[{"metric":"complexity","value":"0"},{"metric":"functions","value":"0"},{"metric":"ncloc","value":"10"},{"metric":"coverage","value":"0.0","bestValue":false},{"metric":"security_rating","value":"1.0","bestValue":true},{"metric":"comment_lines_density","value":"0.0","bestValue":false},{"metric":"files","value":"1"},{"metric":"duplicated_lines_density","value":"0.0","bestValue":true},{"metric":"test_errors","value":"0","bestValue":true},{"metric":"test_failures","value":"0","bestValue":true}]},{"id":"AYk7nSYRbtttg9wbGYMk","key":"fga-eps-mds-1_2023-1-capju-services-unit:src/migrations","name":"migrations","qualifier":"DIR","path":"src/migrations","measures":[{"metric":"duplicated_lines_density","value":"0.0","bestValue":true},{"metric":"functions","value":"2"},{"metric":"security_rating","value":"1.0","bestValue":true},{"metric":"files","value":"1"},{"metric":"complexity","value":"2"},{"metric":"ncloc","value":"28"},{"metric":"coverage","value":"0.0","bestValue":false},{"metric":"comment_lines_density","value":"3.4","bestValue":false}]},{"id":"AYk7h8KaMxBJGWHr585D","key":"fga-eps-mds-1_2023-1-capju-services-unit:src/models","name":"models","qualifier":"DIR","path":"src/models","measures":[{"metric":"duplicated_lines_density","value":"0.0","bestValue":true},{"metric":"functions","value":"1"},{"metric":"security_rating","value":"1.0","bestValue":true},{"metric":"files","value":"2"},{"metric":"complexity","value":"1"},{"metric":"ncloc","value":"31"},{"metric":"coverage","value":"0.0","bestValue":false},{"metric":"comment_lines_density","value":"0.0","bestValue":false}]},{"id":"AYk7h8KaMxBJGWHr585A","key":"fga-eps-mds-1_2023-1-capju-services-unit:src/schemas/role.js","name":"role.js","qualifier":"FIL","path":"src/schemas/role.js","language":"js","measures":[{"metric":"complexity","value":"0"},{"metric":"functions","value":"0"},{"metric":"ncloc","value":"7"},{"metric":"coverage","value":"0.0","bestValue":false},{"metric":"security_rating","value":"1.0","bestValue":true},{"metric":"comment_lines_density","value":"0.0","bestValue":false},{"metric":"files","value":"1"},{"metric":"duplicated_lines_density","value":"0.0","bestValue":true},{"metric":"test_errors","value":"0","bestValue":true},{"metric":"test_failures","value":"0","bestValue":true}]},{"id":"AYk7h8KaMxBJGWHr585H","key":"fga-eps-mds-1_2023-1-capju-services-unit:src/routes","name":"routes","qualifier":"DIR","path":"src/routes","measures":[{"metric":"duplicated_lines_density","value":"0.0","bestValue":true},{"metric":"functions","value":"0"},{"metric":"security_rating","value":"1.0","bestValue":true},{"metric":"files","value":"2"},{"metric":"complexity","value":"0"},{"metric":"ncloc","value":"18"},{"metric":"coverage","value":"0.0","bestValue":false},{"metric":"comment_lines_density","value":"0.0","bestValue":false}]},{"id":"AYk7h8KaMxBJGWHr585B","key":"fga-eps-mds-1_2023-1-capju-services-unit:src/schemas","name":"schemas","qualifier":"DIR","path":"src/schemas","measures":[{"metric":"duplicated_lines_density","value":"0.0","bestValue":true},{"metric":"functions","value":"0"},{"metric":"security_rating","value":"1.0","bestValue":true},{"metric":"files","value":"1"},{"metric":"complexity","value":"0"},{"metric":"ncloc","value":"7"},{"metric":"coverage","value":"0.0","bestValue":false},{"metric":"comment_lines_density","value":"0.0","bestValue":false}]},{"id":"AYk7nSYRbtttg9wbGYMh","key":"fga-eps-mds-1_2023-1-capju-services-unit:src/config/sequelize.js","name":"sequelize.js","qualifier":"FIL","path":"src/config/sequelize.js","language":"js","measures":[{"metric":"complexity","value":"0"},{"metric":"functions","value":"0"},{"metric":"ncloc","value":"4"},{"metric":"coverage","value":"0.0","bestValue":false},{"metric":"security_rating","value":"1.0","bestValue":true},{"metric":"comment_lines_density","value":"0.0","bestValue":false},{"metric":"files","value":"1"},{"metric":"duplicated_lines_density","value":"0.0","bestValue":true},{"metric":"test_errors","value":"0","bestValue":true},{"metric":"test_failures","value":"0","bestValue":true}]},{"id":"AYk7nSYRbtttg9wbGYMi","key":"fga-eps-mds-1_2023-1-capju-services-unit:src/server.js","name":"server.js","qualifier":"FIL","path":"src/server.js","language":"js","measures":[{"metric":"complexity","value":"2"},{"metric":"functions","value":"2"},{"metric":"ncloc","value":"18"},{"metric":"coverage","value":"0.0","bestValue":false},{"metric":"security_rating","value":"1.0","bestValue":true},{"metric":"comment_lines_density","value":"0.0","bestValue":false},{"metric":"files","value":"1"},{"metric":"duplicated_lines_density","value":"0.0","bestValue":true},{"metric":"test_errors","value":"0","bestValue":true},{"metric":"test_failures","value":"0","bestValue":true}]},{"id":"AYk7nSYRbtttg9wbGYMf","key":"fga-eps-mds-1_2023-1-capju-services-unit:src/services","name":"services","qualifier":"DIR","path":"src/services","measures":[{"metric":"duplicated_lines_density","value":"0.0","bestValue":true},{"metric":"functions","value":"6"},{"metric":"security_rating","value":"1.0","bestValue":true},{"metric":"files","value":"2"},{"metric":"complexity","value":"10"},{"metric":"ncloc","value":"43"},{"metric":"coverage","value":"0.0","bestValue":false},{"metric":"comment_lines_density","value":"0.0","bestValue":false}]},{"id":"AYk7h8KaMxBJGWHr585K","key":"fga-eps-mds-1_2023-1-capju-services-unit:src","name":"src","qualifier":"DIR","path":"src","measures":[{"metric":"duplicated_lines_density","value":"0.0","bestValue":true},{"metric":"functions","value":"18"},{"metric":"security_rating","value":"1.0","bestValue":true},{"metric":"files","value":"13"},{"metric":"complexity","value":"27"},{"metric":"ncloc","value":"285"},{"metric":"coverage","value":"0.0","bestValue":false},{"metric":"comment_lines_density","value":"0.7","bestValue":false}]},{"id":"AYk7h8KaMxBJGWHr585L","key":"fga-eps-mds-1_2023-1-capju-services-unit:tests/__tests__/test_unit_routes.js","name":"test_unit_routes.js","qualifier":"UTS","path":"tests/__tests__/test_unit_routes.js","language":"js","measures":[{"metric":"security_rating","value":"1.0","bestValue":true},{"metric":"duplicated_lines_density","value":"0.0","bestValue":true},{"metric":"test_errors","value":"0","bestValue":true},{"metric":"test_failures","value":"0","bestValue":true}]},{"id":"AYk7h8KaMxBJGWHr585M","key":"fga-eps-mds-1_2023-1-capju-services-unit:tests/__tests__","name":"tests/__tests__","qualifier":"DIR","path":"tests/__tests__","measures":[{"metric":"security_rating","value":"1.0","bestValue":true}]},{"id":"AYk7h8KaMxBJGWHr585C","key":"fga-eps-mds-1_2023-1-capju-services-unit:src/models/unit.js","name":"unit.js","qualifier":"FIL","path":"src/models/unit.js","language":"js","measures":[{"metric":"complexity","value":"1"},{"metric":"functions","value":"1"},{"metric":"ncloc","value":"25"},{"metric":"coverage","value":"0.0","bestValue":false},{"metric":"security_rating","value":"1.0","bestValue":true},{"metric":"comment_lines_density","value":"0.0","bestValue":false},{"metric":"files","value":"1"},{"metric":"duplicated_lines_density","value":"0.0","bestValue":true},{"metric":"test_errors","value":"0","bestValue":true},{"metric":"test_failures","value":"0","bestValue":true}]},{"id":"AYk7h8KaMxBJGWHr585E","key":"fga-eps-mds-1_2023-1-capju-services-unit:src/controllers/unit.js","name":"unit.js","qualifier":"FIL","path":"src/controllers/unit.js","language":"js","measures":[{"metric":"complexity","value":"12"},{"metric":"functions","value":"7"},{"metric":"ncloc","value":"120"},{"metric":"coverage","value":"0.0","bestValue":false},{"metric":"security_rating","value":"1.0","bestValue":true},{"metric":"comment_lines_density","value":"0.8","bestValue":false},{"metric":"files","value":"1"},{"metric":"duplicated_lines_density","value":"0.0","bestValue":true},{"metric":"test_errors","value":"0","bestValue":true},{"metric":"test_failures","value":"0","bestValue":true}]},{"id":"AYk7nSYRbtttg9wbGYMc","key":"fga-eps-mds-1_2023-1-capju-services-unit:src/routes/unit.js","name":"unit.js","qualifier":"FIL","path":"src/routes/unit.js","language":"js","measures":[{"metric":"complexity","value":"0"},{"metric":"functions","value":"0"},{"metric":"ncloc","value":"13"},{"metric":"coverage","value":"0.0","bestValue":false},{"metric":"security_rating","value":"1.0","bestValue":true},{"metric":"comment_lines_density","value":"0.0","bestValue":false},{"metric":"files","value":"1"},{"metric":"duplicated_lines_density","value":"0.0","bestValue":true},{"metric":"test_errors","value":"0","bestValue":true},{"metric":"test_failures","value":"0","bestValue":true}]},{"id":"AYk7nSYRbtttg9wbGYMe","key":"fga-eps-mds-1_2023-1-capju-services-unit:src/services/unit.js","name":"unit.js","qualifier":"FIL","path":"src/services/unit.js","language":"js","measures":[{"metric":"complexity","value":"10"},{"metric":"functions","value":"6"},{"metric":"ncloc","value":"36"},{"metric":"coverage","value":"0.0","bestValue":false},{"metric":"security_rating","value":"1.0","bestValue":true},{"metric":"comment_lines_density","value":"0.0","bestValue":false},{"metric":"files","value":"1"},{"metric":"duplicated_lines_density","value":"0.0","bestValue":true},{"metric":"test_errors","value":"0","bestValue":true},{"metric":"test_failures","value":"0","bestValue":true}]}]}